
{"objectIdFieldName":"OBJECTID","uniqueIdField":{"name":"OBJECTID","isSystemMaintained":true},"globalIdFieldName":"","fields":[{"name":"ID","type":"esriFieldTypeString","alias":"ID","sqlType":"sqlTypeOther","length":25,"domain":null,"defaultValue":null},{"name":"SAFMR_0BR","type":"esriFieldTypeDouble","alias":"SAFMR_0BR","sqlType":"sqlTypeOther","domain":null,"defaultValue":null},{"name":"SAFMR_1BR","type":"esriFieldTypeDouble","alias":"SAFMR_1BR","sqlType":"sqlTypeOther","domain":null,"defaultValue":null},{"name":"SAFMR_2BR","type":"esriFieldTypeDouble","alias":"SAFMR_2BR","sqlType":"sqlTypeOther","domain":null,"defaultValue":null},{"name":"SAFMR_3BR","type":"esriFieldTypeDouble","alias":"SAFMR_3BR","sqlType":"sqlTypeOther","domain":null,"defaultValue":null},{"name":"SAFMR_4BR","type":"esriFieldTypeDouble","alias":"SAFMR_4BR","sqlType":"sqlTypeOther","domain":null,"defaultValue":null}],"features":[{"attributes":{"ID":"10001","SAFMR_0BR":3800,"SAFMR_1BR":3990,"SAFMR_2BR":4370,"SAFMR_3BR":5470,"SAFMR_4BR":5950}},{"attributes":{"ID":"10002","SAFMR_0BR":2170,"SAFMR_1BR":2260,"SAFMR_2BR":2510,"SAFMR_3BR":3120,"SAFMR_4BR":3370}},{"attributes":{"ID":"10003","SAFMR_0BR":3800,"SAFMR_1BR":3990,"SAFMR_2BR":4370,"SAFMR_3BR":5470,"SAFMR_4BR":5950}},{"attributes":{"ID":"10004","SAFMR_0BR":3120,"SAFMR_1BR":3270,"SAFMR_2BR":3590,"SAFMR_3BR":4500,"SAFMR_4BR":4880}},{"attributes":{"ID":"10005","SAFMR_0BR":3250,"SAFMR_1BR":3400,"SAFMR_2BR":3760,"SAFMR_3BR":4680,"SAFMR_4BR":5050}},{"attributes":{"ID":"10006","SAFMR_0BR":3250,"SAFMR_1BR":3400,"SAFMR_2BR":3760,"SAFMR_3BR":4680,"SAFMR_4BR":5050}},{"attributes":{"ID":"10007","SAFMR_0BR":3120,"SAFMR_1BR":3270,"SAFMR_2BR":3590,"SAFMR_3BR":4500,"SAFMR_4BR":4880}},{"attributes":{"ID":"10008","SAFMR_0BR":3120,"SAFMR_1BR":3270,"SAFMR_2BR":3590,"SAFMR_3BR":4500,"SAFMR_4BR":4880}},{"attributes":{"ID":"10009","SAFMR_0BR":2700,"SAFMR_1BR":2840,"SAFMR_2BR":3110,"SAFMR_3BR":3890,"SAFMR_4BR":4230}},{"attributes":{"ID":"10010","SAFMR_0BR":3270,"SAFMR_1BR":3430,"SAFMR_2BR":3760,"SAFMR_3BR":4710,"SAFMR_4BR":5120}},{"attributes":{"ID":"10011","SAFMR_0BR":3800,"SAFMR_1BR":3990,"SAFMR_2BR":4370,"SAFMR_3BR":5470,"SAFMR_4BR":5950}},{"attributes":{"ID":"10012","SAFMR_0BR":3800,"SAFMR_1BR":3990,"SAFMR_2BR":4370,"SAFMR_3BR":5470,"SAFMR_4BR":5950}},{"attributes":{"ID":"10013","SAFMR_0BR":3800,"SAFMR_1BR":3990,"SAFMR_2BR":4370,"SAFMR_3BR":5470,"SAFMR_4BR":5950}},{"attributes":{"ID":"10014","SAFMR_0BR":3800,"SAFMR_1BR":3990,"SAFMR_2BR":4370,"SAFMR_3BR":5470,"SAFMR_4BR":5950}},{"attributes":{"ID":"10016","SAFMR_0BR":3800,"SAFMR_1BR":3990,"SAFMR_2BR":4370,"SAFMR_3BR":5470,"SAFMR_4BR":5950}},{"attributes":{"ID":"10017","SAFMR_0BR":3800,"SAFMR_1BR":3990,"SAFMR_2BR":4370,"SAFMR_3BR":5470,"SAFMR_4BR":5950}},{"attributes":{"ID":"10018","SAFMR_0BR":3690,"SAFMR_1BR":3880,"SAFMR_2BR":4240,"SAFMR_3BR":5310,"SAFMR_4BR":5780}},{"attributes":{"ID":"10019","SAFMR_0BR":3550,"SAFMR_1BR":3720,"SAFMR_2BR":4080,"SAFMR_3BR":5110,"SAFMR_4BR":5550}},{"attributes":{"ID":"10020","SAFMR_0BR":3120,"SAFMR_1BR":3270,"SAFMR_2BR":3590,"SAFMR_3BR":4500,"SAFMR_4BR":4880}},{"attributes":{"ID":"10021","SAFMR_0BR":3800,"SAFMR_1BR":3990,"SAFMR_2BR":4370,"SAFMR_3BR":5470,"SAFMR_4BR":5950}},{"attributes":{"ID":"10022","SAFMR_0BR":3800,"SAFMR_1BR":3990,"SAFMR_2BR":4370,"SAFMR_3BR":5470,"SAFMR_4BR":5950}},{"attributes":{"ID":"10023","SAFMR_0BR":3800,"SAFMR_1BR":3990,"SAFMR_2BR":4370,"SAFMR_3BR":5470,"SAFMR_4BR":5950}},{"attributes":{"ID":"10024","SAFMR_0BR":3800,"SAFMR_1BR":3990,"SAFMR_2BR":4370,"SAFMR_3BR":5470,"SAFMR_4BR":5950}},{"attributes":{"ID":"10025","SAFMR_0BR":2660,"SAFMR_1BR":2790,"SAFMR_2BR":3060,"SAFMR_3BR":3830,"SAFMR_4BR":4160}},{"attributes":{"ID":"10026","SAFMR_0BR":2670,"SAFMR_1BR":2800,"SAFMR_2BR":3070,"SAFMR_3BR":3840,"SAFMR_4BR":4180}},{"attributes":{"ID":"10027","SAFMR_0BR":2350,"SAFMR_1BR":2460,"SAFMR_2BR":2700,"SAFMR_3BR":3380,"SAFMR_4BR":3670}},{"attributes":{"ID":"10028","SAFMR_0BR":3800,"SAFMR_1BR":3990,"SAFMR_2BR":4370,"SAFMR_3BR":5470,"SAFMR_4BR":5950}},{"attributes":{"ID":"10029","SAFMR_0BR":2170,"SAFMR_1BR":2260,"SAFMR_2BR":2510,"SAFMR_3BR":3120,"SAFMR_4BR":3370}},{"attributes":{"ID":"10030","SAFMR_0BR":2170,"SAFMR_1BR":2260,"SAFMR_2BR":2510,"SAFMR_3BR":3120,"SAFMR_4BR":3370}},{"attributes":{"ID":"10031","SAFMR_0BR":2380,"SAFMR_1BR":2500,"SAFMR_2BR":2740,"SAFMR_3BR":3430,"SAFMR_4BR":3730}},{"attributes":{"ID":"10032","SAFMR_0BR":2170,"SAFMR_1BR":2260,"SAFMR_2BR":2510,"SAFMR_3BR":3120,"SAFMR_4BR":3370}},{"attributes":{"ID":"10033","SAFMR_0BR":2260,"SAFMR_1BR":2370,"SAFMR_2BR":2600,"SAFMR_3BR":3260,"SAFMR_4BR":3540}},{"attributes":{"ID":"10034","SAFMR_0BR":2400,"SAFMR_1BR":2520,"SAFMR_2BR":2760,"SAFMR_3BR":3460,"SAFMR_4BR":3760}},{"attributes":{"ID":"10035","SAFMR_0BR":2220,"SAFMR_1BR":2340,"SAFMR_2BR":2560,"SAFMR_3BR":3210,"SAFMR_4BR":3480}},{"attributes":{"ID":"10036","SAFMR_0BR":3510,"SAFMR_1BR":3690,"SAFMR_2BR":4040,"SAFMR_3BR":5060,"SAFMR_4BR":5500}},{"attributes":{"ID":"10037","SAFMR_0BR":2240,"SAFMR_1BR":2350,"SAFMR_2BR":2580,"SAFMR_3BR":3230,"SAFMR_4BR":3510}},{"attributes":{"ID":"10038","SAFMR_0BR":3800,"SAFMR_1BR":3990,"SAFMR_2BR":4370,"SAFMR_3BR":5470,"SAFMR_4BR":5950}},{"attributes":{"ID":"10039","SAFMR_0BR":2170,"SAFMR_1BR":2260,"SAFMR_2BR":2510,"SAFMR_3BR":3120,"SAFMR_4BR":3370}},{"attributes":{"ID":"10040","SAFMR_0BR":2350,"SAFMR_1BR":2470,"SAFMR_2BR":2710,"SAFMR_3BR":3390,"SAFMR_4BR":3690}},{"attributes":{"ID":"10041","SAFMR_0BR":3120,"SAFMR_1BR":3270,"SAFMR_2BR":3590,"SAFMR_3BR":4500,"SAFMR_4BR":4880}},{"attributes":{"ID":"10043","SAFMR_0BR":3120,"SAFMR_1BR":3270,"SAFMR_2BR":3590,"SAFMR_3BR":4500,"SAFMR_4BR":4880}},{"attributes":{"ID":"10044","SAFMR_0BR":3800,"SAFMR_1BR":3990,"SAFMR_2BR":4370,"SAFMR_3BR":5470,"SAFMR_4BR":5950}},{"attributes":{"ID":"10045","SAFMR_0BR":3120,"SAFMR_1BR":3270,"SAFMR_2BR":3590,"SAFMR_3BR":4500,"SAFMR_4BR":4880}},{"attributes":{"ID":"10055","SAFMR_0BR":3120,"SAFMR_1BR":3270,"SAFMR_2BR":3590,"SAFMR_3BR":4500,"SAFMR_4BR":4880}},{"attributes":{"ID":"10065","SAFMR_0BR":3800,"SAFMR_1BR":3990,"SAFMR_2BR":4370,"SAFMR_3BR":5470,"SAFMR_4BR":5950}},{"attributes":{"ID":"10069","SAFMR_0BR":3800,"SAFMR_1BR":3990,"SAFMR_2BR":4370,"SAFMR_3BR":5470,"SAFMR_4BR":5950}},{"attributes":{"ID":"10075","SAFMR_0BR":3220,"SAFMR_1BR":3380,"SAFMR_2BR":3710,"SAFMR_3BR":4650,"SAFMR_4BR":5050}},{"attributes":{"ID":"10080","SAFMR_0BR":3120,"SAFMR_1BR":3270,"SAFMR_2BR":3590,"SAFMR_3BR":4500,"SAFMR_4BR":4880}},{"attributes":{"ID":"10081","SAFMR_0BR":3120,"SAFMR_1BR":3270,"SAFMR_2BR":3590,"SAFMR_3BR":4500,"SAFMR_4BR":4880}},{"attributes":{"ID":"10101","SAFMR_0BR":3120,"SAFMR_1BR":3270,"SAFMR_2BR":3590,"SAFMR_3BR":4500,"SAFMR_4BR":4880}},{"attributes":{"ID":"10103","SAFMR_0BR":3120,"SAFMR_1BR":3270,"SAFMR_2BR":3590,"SAFMR_3BR":4500,"SAFMR_4BR":4880}},{"attributes":{"ID":"10104","SAFMR_0BR":3120,"SAFMR_1BR":3270,"SAFMR_2BR":3590,"SAFMR_3BR":4500,"SAFMR_4BR":4880}},{"attributes":{"ID":"10105","SAFMR_0BR":3120,"SAFMR_1BR":3270,"SAFMR_2BR":3590,"SAFMR_3BR":4500,"SAFMR_4BR":4880}},{"attributes":{"ID":"10106","SAFMR_0BR":3120,"SAFMR_1BR":3270,"SAFMR_2BR":3590,"SAFMR_3BR":4500,"SAFMR_4BR":4880}},{"attributes":{"ID":"10107","SAFMR_0BR":3120,"SAFMR_1BR":3270,"SAFMR_2BR":3590,"SAFMR_3BR":4500,"SAFMR_4BR":4880}},{"attributes":{"ID":"10108","SAFMR_0BR":3120,"SAFMR_1BR":3270,"SAFMR_2BR":3590,"SAFMR_3BR":4500,"SAFMR_4BR":4880}},{"attributes":{"ID":"10110","SAFMR_0BR":3120,"SAFMR_1BR":3270,"SAFMR_2BR":3590,"SAFMR_3BR":4500,"SAFMR_4BR":4880}},{"attributes":{"ID":"10111","SAFMR_0BR":3120,"SAFMR_1BR":3270,"SAFMR_2BR":3590,"SAFMR_3BR":4500,"SAFMR_4BR":4880}},{"attributes":{"ID":"10112","SAFMR_0BR":3120,"SAFMR_1BR":3270,"SAFMR_2BR":3590,"SAFMR_3BR":4500,"SAFMR_4BR":4880}},{"attributes":{"ID":"10113","SAFMR_0BR":3120,"SAFMR_1BR":3270,"SAFMR_2BR":3590,"SAFMR_3BR":4500,"SAFMR_4BR":4880}},{"attributes":{"ID":"10115","SAFMR_0BR":3120,"SAFMR_1BR":3270,"SAFMR_2BR":3590,"SAFMR_3BR":4500,"SAFMR_4BR":4880}},{"attributes":{"ID":"10116","SAFMR_0BR":3120,"SAFMR_1BR":3270,"SAFMR_2BR":3590,"SAFMR_3BR":4500,"SAFMR_4BR":4880}},{"attributes":{"ID":"10117","SAFMR_0BR":3120,"SAFMR_1BR":3270,"SAFMR_2BR":3590,"SAFMR_3BR":4500,"SAFMR_4BR":4880}},{"attributes":{"ID":"10118","SAFMR_0BR":3120,"SAFMR_1BR":3270,"SAFMR_2BR":3590,"SAFMR_3BR":4500,"SAFMR_4BR":4880}},{"attributes":{"ID":"10119","SAFMR_0BR":3120,"SAFMR_1BR":3270,"SAFMR_2BR":3590,"SAFMR_3BR":4500,"SAFMR_4BR":4880}},{"attributes":{"ID":"10120","SAFMR_0BR":3120,"SAFMR_1BR":3270,"SAFMR_2BR":3590,"SAFMR_3BR":4500,"SAFMR_4BR":4880}},{"attributes":{"ID":"10121","SAFMR_0BR":3120,"SAFMR_1BR":3270,"SAFMR_2BR":3590,"SAFMR_3BR":4500,"SAFMR_4BR":4880}},{"attributes":{"ID":"10122","SAFMR_0BR":3120,"SAFMR_1BR":3270,"SAFMR_2BR":3590,"SAFMR_3BR":4500,"SAFMR_4BR":4880}},{"attributes":{"ID":"10123","SAFMR_0BR":3120,"SAFMR_1BR":3270,"SAFMR_2BR":3590,"SAFMR_3BR":4500,"SAFMR_4BR":4880}},{"attributes":{"ID":"10124","SAFMR_0BR":3120,"SAFMR_1BR":3270,"SAFMR_2BR":3590,"SAFMR_3BR":4500,"SAFMR_4BR":4880}},{"attributes":{"ID":"10125","SAFMR_0BR":3120,"SAFMR_1BR":3270,"SAFMR_2BR":3590,"SAFMR_3BR":4500,"SAFMR_4BR":4880}},{"attributes":{"ID":"10126","SAFMR_0BR":3120,"SAFMR_1BR":3270,"SAFMR_2BR":3590,"SAFMR_3BR":4500,"SAFMR_4BR":4880}},{"attributes":{"ID":"10128","SAFMR_0BR":3800,"SAFMR_1BR":3990,"SAFMR_2BR":4370,"SAFMR_3BR":5470,"SAFMR_4BR":5950}},{"attributes":{"ID":"10129","SAFMR_0BR":3120,"SAFMR_1BR":3270,"SAFMR_2BR":3590,"SAFMR_3BR":4500,"SAFMR_4BR":4880}},{"attributes":{"ID":"10131","SAFMR_0BR":3120,"SAFMR_1BR":3270,"SAFMR_2BR":3590,"SAFMR_3BR":4500,"SAFMR_4BR":4880}},{"attributes":{"ID":"10133","SAFMR_0BR":3120,"SAFMR_1BR":3270,"SAFMR_2BR":3590,"SAFMR_3BR":4500,"SAFMR_4BR":4880}},{"attributes":{"ID":"10138","SAFMR_0BR":3120,"SAFMR_1BR":3270,"SAFMR_2BR":3590,"SAFMR_3BR":4500,"SAFMR_4BR":4880}},{"attributes":{"ID":"10150","SAFMR_0BR":3120,"SAFMR_1BR":3270,"SAFMR_2BR":3590,"SAFMR_3BR":4500,"SAFMR_4BR":4880}},{"attributes":{"ID":"10151","SAFMR_0BR":3120,"SAFMR_1BR":3270,"SAFMR_2BR":3590,"SAFMR_3BR":4500,"SAFMR_4BR":4880}},{"attributes":{"ID":"10152","SAFMR_0BR":3800,"SAFMR_1BR":3990,"SAFMR_2BR":4370,"SAFMR_3BR":5470,"SAFMR_4BR":5950}},{"attributes":{"ID":"10153","SAFMR_0BR":3120,"SAFMR_1BR":3270,"SAFMR_2BR":3590,"SAFMR_3BR":4500,"SAFMR_4BR":4880}},{"attributes":{"ID":"10154","SAFMR_0BR":3120,"SAFMR_1BR":3270,"SAFMR_2BR":3590,"SAFMR_3BR":4500,"SAFMR_4BR":4880}},{"attributes":{"ID":"10155","SAFMR_0BR":3120,"SAFMR_1BR":3270,"SAFMR_2BR":3590,"SAFMR_3BR":4500,"SAFMR_4BR":4880}},{"attributes":{"ID":"10156","SAFMR_0BR":3120,"SAFMR_1BR":3270,"SAFMR_2BR":3590,"SAFMR_3BR":4500,"SAFMR_4BR":4880}},{"attributes":{"ID":"10157","SAFMR_0BR":3120,"SAFMR_1BR":3270,"SAFMR_2BR":3590,"SAFMR_3BR":4500,"SAFMR_4BR":4880}},{"attributes":{"ID":"10158","SAFMR_0BR":3120,"SAFMR_1BR":3270,"SAFMR_2BR":3590,"SAFMR_3BR":4500,"SAFMR_4BR":4880}},{"attributes":{"ID":"10159","SAFMR_0BR":3120,"SAFMR_1BR":3270,"SAFMR_2BR":3590,"SAFMR_3BR":4500,"SAFMR_4BR":4880}},{"attributes":{"ID":"10160","SAFMR_0BR":3120,"SAFMR_1BR":3270,"SAFMR_2BR":3590,"SAFMR_3BR":4500,"SAFMR_4BR":4880}},{"attributes":{"ID":"10162","SAFMR_0BR":3450,"SAFMR_1BR":3620,"SAFMR_2BR":3970,"SAFMR_3BR":4970,"SAFMR_4BR":5400}},{"attributes":{"ID":"10163","SAFMR_0BR":3120,"SAFMR_1BR":3270,"SAFMR_2BR":3590,"SAFMR_3BR":4500,"SAFMR_4BR":4880}},{"attributes":{"ID":"10164","SAFMR_0BR":3120,"SAFMR_1BR":3270,"SAFMR_2BR":3590,"SAFMR_3BR":4500,"SAFMR_4BR":4880}},{"attributes":{"ID":"10165","SAFMR_0BR":3120,"SAFMR_1BR":3270,"SAFMR_2BR":3590,"SAFMR_3BR":4500,"SAFMR_4BR":4880}},{"attributes":{"ID":"10166","SAFMR_0BR":3120,"SAFMR_1BR":3270,"SAFMR_2BR":3590,"SAFMR_3BR":4500,"SAFMR_4BR":4880}},{"attributes":{"ID":"10167","SAFMR_0BR":3120,"SAFMR_1BR":3270,"SAFMR_2BR":3590,"SAFMR_3BR":4500,"SAFMR_4BR":4880}},{"attributes":{"ID":"10168","SAFMR_0BR":3120,"SAFMR_1BR":3270,"SAFMR_2BR":3590,"SAFMR_3BR":4500,"SAFMR_4BR":4880}},{"attributes":{"ID":"10169","SAFMR_0BR":3120,"SAFMR_1BR":3270,"SAFMR_2BR":3590,"SAFMR_3BR":4500,"SAFMR_4BR":4880}},{"attributes":{"ID":"10170","SAFMR_0BR":3120,"SAFMR_1BR":3270,"SAFMR_2BR":3590,"SAFMR_3BR":4500,"SAFMR_4BR":4880}},{"attributes":{"ID":"10171","SAFMR_0BR":3120,"SAFMR_1BR":3270,"SAFMR_2BR":3590,"SAFMR_3BR":4500,"SAFMR_4BR":4880}},{"attributes":{"ID":"10172","SAFMR_0BR":3120,"SAFMR_1BR":3270,"SAFMR_2BR":3590,"SAFMR_3BR":4500,"SAFMR_4BR":4880}},{"attributes":{"ID":"10173","SAFMR_0BR":3120,"SAFMR_1BR":3270,"SAFMR_2BR":3590,"SAFMR_3BR":4500,"SAFMR_4BR":4880}},{"attributes":{"ID":"10174","SAFMR_0BR":3120,"SAFMR_1BR":3270,"SAFMR_2BR":3590,"SAFMR_3BR":4500,"SAFMR_4BR":4880}},{"attributes":{"ID":"10175","SAFMR_0BR":3120,"SAFMR_1BR":3270,"SAFMR_2BR":3590,"SAFMR_3BR":4500,"SAFMR_4BR":4880}},{"attributes":{"ID":"10176","SAFMR_0BR":3120,"SAFMR_1BR":3270,"SAFMR_2BR":3590,"SAFMR_3BR":4500,"SAFMR_4BR":4880}},{"attributes":{"ID":"10177","SAFMR_0BR":3120,"SAFMR_1BR":3270,"SAFMR_2BR":3590,"SAFMR_3BR":4500,"SAFMR_4BR":4880}},{"attributes":{"ID":"10178","SAFMR_0BR":3120,"SAFMR_1BR":3270,"SAFMR_2BR":3590,"SAFMR_3BR":4500,"SAFMR_4BR":4880}},{"attributes":{"ID":"10179","SAFMR_0BR":3120,"SAFMR_1BR":3270,"SAFMR_2BR":3590,"SAFMR_3BR":4500,"SAFMR_4BR":4880}},{"attributes":{"ID":"10185","SAFMR_0BR":3120,"SAFMR_1BR":3270,"SAFMR_2BR":3590,"SAFMR_3BR":4500,"SAFMR_4BR":4880}},{"attributes":{"ID":"10199","SAFMR_0BR":3120,"SAFMR_1BR":3270,"SAFMR_2BR":3590,"SAFMR_3BR":4500,"SAFMR_4BR":4880}},{"attributes":{"ID":"10203","SAFMR_0BR":3120,"SAFMR_1BR":3270,"SAFMR_2BR":3590,"SAFMR_3BR":4500,"SAFMR_4BR":4880}},{"attributes":{"ID":"10211","SAFMR_0BR":3120,"SAFMR_1BR":3270,"SAFMR_2BR":3590,"SAFMR_3BR":4500,"SAFMR_4BR":4880}},{"attributes":{"ID":"10212","SAFMR_0BR":3120,"SAFMR_1BR":3270,"SAFMR_2BR":3590,"SAFMR_3BR":4500,"SAFMR_4BR":4880}},{"attributes":{"ID":"10213","SAFMR_0BR":3120,"SAFMR_1BR":3270,"SAFMR_2BR":3590,"SAFMR_3BR":4500,"SAFMR_4BR":4880}},{"attributes":{"ID":"10258","SAFMR_0BR":3120,"SAFMR_1BR":3270,"SAFMR_2BR":3590,"SAFMR_3BR":4500,"SAFMR_4BR":4880}},{"attributes":{"ID":"10268","SAFMR_0BR":3120,"SAFMR_1BR":3270,"SAFMR_2BR":3590,"SAFMR_3BR":4500,"SAFMR_4BR":4880}},{"attributes":{"ID":"10269","SAFMR_0BR":3120,"SAFMR_1BR":3270,"SAFMR_2BR":3590,"SAFMR_3BR":4500,"SAFMR_4BR":4880}},{"attributes":{"ID":"10271","SAFMR_0BR":3120,"SAFMR_1BR":3270,"SAFMR_2BR":3590,"SAFMR_3BR":4500,"SAFMR_4BR":4880}},{"attributes":{"ID":"10272","SAFMR_0BR":3120,"SAFMR_1BR":3270,"SAFMR_2BR":3590,"SAFMR_3BR":4500,"SAFMR_4BR":4880}},{"attributes":{"ID":"10274","SAFMR_0BR":3120,"SAFMR_1BR":3270,"SAFMR_2BR":3590,"SAFMR_3BR":4500,"SAFMR_4BR":4880}},{"attributes":{"ID":"10275","SAFMR_0BR":3120,"SAFMR_1BR":3270,"SAFMR_2BR":3590,"SAFMR_3BR":4500,"SAFMR_4BR":4880}},{"attributes":{"ID":"10276","SAFMR_0BR":3120,"SAFMR_1BR":3270,"SAFMR_2BR":3590,"SAFMR_3BR":4500,"SAFMR_4BR":4880}},{"attributes":{"ID":"10277","SAFMR_0BR":3120,"SAFMR_1BR":3270,"SAFMR_2BR":3590,"SAFMR_3BR":4500,"SAFMR_4BR":4880}},{"attributes":{"ID":"10278","SAFMR_0BR":3120,"SAFMR_1BR":3270,"SAFMR_2BR":3590,"SAFMR_3BR":4500,"SAFMR_4BR":4880}},{"attributes":{"ID":"10279","SAFMR_0BR":3120,"SAFMR_1BR":3270,"SAFMR_2BR":3590,"SAFMR_3BR":4500,"SAFMR_4BR":4880}},{"attributes":{"ID":"10280","SAFMR_0BR":3120,"SAFMR_1BR":3270,"SAFMR_2BR":3590,"SAFMR_3BR":4500,"SAFMR_4BR":4880}},{"attributes":{"ID":"10281","SAFMR_0BR":3120,"SAFMR_1BR":3270,"SAFMR_2BR":3590,"SAFMR_3BR":4500,"SAFMR_4BR":4880}},{"attributes":{"ID":"10282","SAFMR_0BR":3250,"SAFMR_1BR":3400,"SAFMR_2BR":3760,"SAFMR_3BR":4680,"SAFMR_4BR":5050}},{"attributes":{"ID":"10285","SAFMR_0BR":3120,"SAFMR_1BR":3270,"SAFMR_2BR":3590,"SAFMR_3BR":4500,"SAFMR_4BR":4880}},{"attributes":{"ID":"10301","SAFMR_0BR":2640,"SAFMR_1BR":2770,"SAFMR_2BR":3040,"SAFMR_3BR":3810,"SAFMR_4BR":4140}},{"attributes":{"ID":"10302","SAFMR_0BR":2440,"SAFMR_1BR":2560,"SAFMR_2BR":2810,"SAFMR_3BR":3520,"SAFMR_4BR":3820}},{"attributes":{"ID":"10303","SAFMR_0BR":2470,"SAFMR_1BR":2590,"SAFMR_2BR":2840,"SAFMR_3BR":3560,"SAFMR_4BR":3860}},{"attributes":{"ID":"10304","SAFMR_0BR":2290,"SAFMR_1BR":2410,"SAFMR_2BR":2640,"SAFMR_3BR":3310,"SAFMR_4BR":3590}},{"attributes":{"ID":"10305","SAFMR_0BR":2290,"SAFMR_1BR":2400,"SAFMR_2BR":2630,"SAFMR_3BR":3290,"SAFMR_4BR":3580}},{"attributes":{"ID":"10306","SAFMR_0BR":2320,"SAFMR_1BR":2440,"SAFMR_2BR":2670,"SAFMR_3BR":3340,"SAFMR_4BR":3630}},{"attributes":{"ID":"10307","SAFMR_0BR":2170,"SAFMR_1BR":2260,"SAFMR_2BR":2510,"SAFMR_3BR":3120,"SAFMR_4BR":3370}},{"attributes":{"ID":"10308","SAFMR_0BR":2420,"SAFMR_1BR":2540,"SAFMR_2BR":2780,"SAFMR_3BR":3480,"SAFMR_4BR":3780}},{"attributes":{"ID":"10309","SAFMR_0BR":2860,"SAFMR_1BR":3000,"SAFMR_2BR":3290,"SAFMR_3BR":4120,"SAFMR_4BR":4480}},{"attributes":{"ID":"10310","SAFMR_0BR":2350,"SAFMR_1BR":2470,"SAFMR_2BR":2710,"SAFMR_3BR":3390,"SAFMR_4BR":3690}},{"attributes":{"ID":"10311","SAFMR_0BR":2360,"SAFMR_1BR":2480,"SAFMR_2BR":2720,"SAFMR_3BR":3410,"SAFMR_4BR":3700}},{"attributes":{"ID":"10312","SAFMR_0BR":2460,"SAFMR_1BR":2580,"SAFMR_2BR":2830,"SAFMR_3BR":3540,"SAFMR_4BR":3850}},{"attributes":{"ID":"10313","SAFMR_0BR":2360,"SAFMR_1BR":2480,"SAFMR_2BR":2720,"SAFMR_3BR":3410,"SAFMR_4BR":3700}},{"attributes":{"ID":"10314","SAFMR_0BR":2510,"SAFMR_1BR":2640,"SAFMR_2BR":2890,"SAFMR_3BR":3620,"SAFMR_4BR":3930}},{"attributes":{"ID":"10451","SAFMR_0BR":2170,"SAFMR_1BR":2260,"SAFMR_2BR":2510,"SAFMR_3BR":3120,"SAFMR_4BR":3370}},{"attributes":{"ID":"10452","SAFMR_0BR":2170,"SAFMR_1BR":2260,"SAFMR_2BR":2510,"SAFMR_3BR":3120,"SAFMR_4BR":3370}},{"attributes":{"ID":"10453","SAFMR_0BR":2170,"SAFMR_1BR":2260,"SAFMR_2BR":2510,"SAFMR_3BR":3120,"SAFMR_4BR":3370}},{"attributes":{"ID":"10454","SAFMR_0BR":2190,"SAFMR_1BR":2300,"SAFMR_2BR":2520,"SAFMR_3BR":3160,"SAFMR_4BR":3430}},{"attributes":{"ID":"10455","SAFMR_0BR":2170,"SAFMR_1BR":2260,"SAFMR_2BR":2510,"SAFMR_3BR":3120,"SAFMR_4BR":3370}},{"attributes":{"ID":"10456","SAFMR_0BR":2170,"SAFMR_1BR":2260,"SAFMR_2BR":2510,"SAFMR_3BR":3120,"SAFMR_4BR":3370}},{"attributes":{"ID":"10457","SAFMR_0BR":2200,"SAFMR_1BR":2310,"SAFMR_2BR":2530,"SAFMR_3BR":3170,"SAFMR_4BR":3440}},{"attributes":{"ID":"10458","SAFMR_0BR":2300,"SAFMR_1BR":2420,"SAFMR_2BR":2650,"SAFMR_3BR":3320,"SAFMR_4BR":3610}},{"attributes":{"ID":"10459","SAFMR_0BR":2170,"SAFMR_1BR":2260,"SAFMR_2BR":2510,"SAFMR_3BR":3120,"SAFMR_4BR":3370}},{"attributes":{"ID":"10460","SAFMR_0BR":2170,"SAFMR_1BR":2260,"SAFMR_2BR":2510,"SAFMR_3BR":3120,"SAFMR_4BR":3370}},{"attributes":{"ID":"10461","SAFMR_0BR":2620,"SAFMR_1BR":2750,"SAFMR_2BR":3020,"SAFMR_3BR":3780,"SAFMR_4BR":4110}},{"attributes":{"ID":"10462","SAFMR_0BR":2480,"SAFMR_1BR":2600,"SAFMR_2BR":2850,"SAFMR_3BR":3570,"SAFMR_4BR":3880}},{"attributes":{"ID":"10463","SAFMR_0BR":2490,"SAFMR_1BR":2610,"SAFMR_2BR":2860,"SAFMR_3BR":3580,"SAFMR_4BR":3890}},{"attributes":{"ID":"10464","SAFMR_0BR":2550,"SAFMR_1BR":2680,"SAFMR_2BR":2940,"SAFMR_3BR":3680,"SAFMR_4BR":4000}},{"attributes":{"ID":"10465","SAFMR_0BR":2640,"SAFMR_1BR":2770,"SAFMR_2BR":3040,"SAFMR_3BR":3810,"SAFMR_4BR":4140}},{"attributes":{"ID":"10466","SAFMR_0BR":2390,"SAFMR_1BR":2510,"SAFMR_2BR":2750,"SAFMR_3BR":3440,"SAFMR_4BR":3740}},{"attributes":{"ID":"10467","SAFMR_0BR":2370,"SAFMR_1BR":2490,"SAFMR_2BR":2730,"SAFMR_3BR":3420,"SAFMR_4BR":3710}},{"attributes":{"ID":"10468","SAFMR_0BR":2320,"SAFMR_1BR":2440,"SAFMR_2BR":2670,"SAFMR_3BR":3340,"SAFMR_4BR":3630}},{"attributes":{"ID":"10469","SAFMR_0BR":2460,"SAFMR_1BR":2580,"SAFMR_2BR":2830,"SAFMR_3BR":3540,"SAFMR_4BR":3850}},{"attributes":{"ID":"10470","SAFMR_0BR":2230,"SAFMR_1BR":2340,"SAFMR_2BR":2570,"SAFMR_3BR":3220,"SAFMR_4BR":3500}},{"attributes":{"ID":"10471","SAFMR_0BR":2360,"SAFMR_1BR":2480,"SAFMR_2BR":2720,"SAFMR_3BR":3410,"SAFMR_4BR":3700}},{"attributes":{"ID":"10472","SAFMR_0BR":2280,"SAFMR_1BR":2390,"SAFMR_2BR":2620,"SAFMR_3BR":3280,"SAFMR_4BR":3560}},{"attributes":{"ID":"10473","SAFMR_0BR":2170,"SAFMR_1BR":2260,"SAFMR_2BR":2510,"SAFMR_3BR":3120,"SAFMR_4BR":3370}},{"attributes":{"ID":"10474","SAFMR_0BR":2170,"SAFMR_1BR":2260,"SAFMR_2BR":2510,"SAFMR_3BR":3120,"SAFMR_4BR":3370}},{"attributes":{"ID":"10475","SAFMR_0BR":2170,"SAFMR_1BR":2260,"SAFMR_2BR":2510,"SAFMR_3BR":3120,"SAFMR_4BR":3370}},{"attributes":{"ID":"10501","SAFMR_0BR":3360,"SAFMR_1BR":3530,"SAFMR_2BR":3870,"SAFMR_3BR":4850,"SAFMR_4BR":5260}},{"attributes":{"ID":"10502","SAFMR_0BR":2990,"SAFMR_1BR":3130,"SAFMR_2BR":3430,"SAFMR_3BR":4300,"SAFMR_4BR":4670}},{"attributes":{"ID":"10503","SAFMR_0BR":3080,"SAFMR_1BR":3240,"SAFMR_2BR":3550,"SAFMR_3BR":4450,"SAFMR_4BR":4830}},{"attributes":{"ID":"10504","SAFMR_0BR":3250,"SAFMR_1BR":3400,"SAFMR_2BR":3760,"SAFMR_3BR":4680,"SAFMR_4BR":5070}},{"attributes":{"ID":"10505","SAFMR_0BR":2460,"SAFMR_1BR":2560,"SAFMR_2BR":2840,"SAFMR_3BR":3540,"SAFMR_4BR":3820}},{"attributes":{"ID":"10506","SAFMR_0BR":3800,"SAFMR_1BR":3990,"SAFMR_2BR":4370,"SAFMR_3BR":5470,"SAFMR_4BR":5950}},{"attributes":{"ID":"10507","SAFMR_0BR":2560,"SAFMR_1BR":2690,"SAFMR_2BR":2950,"SAFMR_3BR":3690,"SAFMR_4BR":4010}},{"attributes":{"ID":"10509","SAFMR_0BR":2450,"SAFMR_1BR":2570,"SAFMR_2BR":2820,"SAFMR_3BR":3530,"SAFMR_4BR":3840}},{"attributes":{"ID":"10510","SAFMR_0BR":3140,"SAFMR_1BR":3290,"SAFMR_2BR":3610,"SAFMR_3BR":4520,"SAFMR_4BR":4910}},{"attributes":{"ID":"10511","SAFMR_0BR":2350,"SAFMR_1BR":2460,"SAFMR_2BR":2700,"SAFMR_3BR":3380,"SAFMR_4BR":3670}},{"attributes":{"ID":"10512","SAFMR_0BR":2170,"SAFMR_1BR":2280,"SAFMR_2BR":2510,"SAFMR_3BR":3130,"SAFMR_4BR":3400}},{"attributes":{"ID":"10512","SAFMR_0BR":2170,"SAFMR_1BR":2280,"SAFMR_2BR":2510,"SAFMR_3BR":3130,"SAFMR_4BR":3400}},{"attributes":{"ID":"10514","SAFMR_0BR":3650,"SAFMR_1BR":3830,"SAFMR_2BR":4200,"SAFMR_3BR":5260,"SAFMR_4BR":5710}},{"attributes":{"ID":"10516","SAFMR_0BR":2390,"SAFMR_1BR":2510,"SAFMR_2BR":2750,"SAFMR_3BR":3440,"SAFMR_4BR":3740}},{"attributes":{"ID":"10517","SAFMR_0BR":2170,"SAFMR_1BR":2260,"SAFMR_2BR":2510,"SAFMR_3BR":3120,"SAFMR_4BR":3370}},{"attributes":{"ID":"10518","SAFMR_0BR":3460,"SAFMR_1BR":3640,"SAFMR_2BR":3980,"SAFMR_3BR":4990,"SAFMR_4BR":5420}},{"attributes":{"ID":"10519","SAFMR_0BR":3220,"SAFMR_1BR":3380,"SAFMR_2BR":3700,"SAFMR_3BR":4630,"SAFMR_4BR":5030}},{"attributes":{"ID":"10520","SAFMR_0BR":2470,"SAFMR_1BR":2590,"SAFMR_2BR":2840,"SAFMR_3BR":3560,"SAFMR_4BR":3860}},{"attributes":{"ID":"10521","SAFMR_0BR":2560,"SAFMR_1BR":2690,"SAFMR_2BR":2950,"SAFMR_3BR":3690,"SAFMR_4BR":4010}},{"attributes":{"ID":"10522","SAFMR_0BR":3060,"SAFMR_1BR":3210,"SAFMR_2BR":3520,"SAFMR_3BR":4410,"SAFMR_4BR":4790}},{"attributes":{"ID":"10523","SAFMR_0BR":3800,"SAFMR_1BR":3990,"SAFMR_2BR":4370,"SAFMR_3BR":5470,"SAFMR_4BR":5950}},{"attributes":{"ID":"10524","SAFMR_0BR":3210,"SAFMR_1BR":3370,"SAFMR_2BR":3690,"SAFMR_3BR":4620,"SAFMR_4BR":5020}},{"attributes":{"ID":"10526","SAFMR_0BR":2990,"SAFMR_1BR":3140,"SAFMR_2BR":3440,"SAFMR_3BR":4310,"SAFMR_4BR":4680}},{"attributes":{"ID":"10527","SAFMR_0BR":3240,"SAFMR_1BR":3400,"SAFMR_2BR":3730,"SAFMR_3BR":4670,"SAFMR_4BR":5070}},{"attributes":{"ID":"10528","SAFMR_0BR":3510,"SAFMR_1BR":3690,"SAFMR_2BR":4040,"SAFMR_3BR":5060,"SAFMR_4BR":5500}},{"attributes":{"ID":"10530","SAFMR_0BR":2950,"SAFMR_1BR":3090,"SAFMR_2BR":3390,"SAFMR_3BR":4250,"SAFMR_4BR":4610}},{"attributes":{"ID":"10532","SAFMR_0BR":3210,"SAFMR_1BR":3340,"SAFMR_2BR":3700,"SAFMR_3BR":4610,"SAFMR_4BR":4980}},{"attributes":{"ID":"10533","SAFMR_0BR":3080,"SAFMR_1BR":3240,"SAFMR_2BR":3550,"SAFMR_3BR":4450,"SAFMR_4BR":4830}},{"attributes":{"ID":"10535","SAFMR_0BR":2660,"SAFMR_1BR":2790,"SAFMR_2BR":3060,"SAFMR_3BR":3830,"SAFMR_4BR":4160}},{"attributes":{"ID":"10536","SAFMR_0BR":3800,"SAFMR_1BR":3990,"SAFMR_2BR":4370,"SAFMR_3BR":5470,"SAFMR_4BR":5950}},{"attributes":{"ID":"10537","SAFMR_0BR":3050,"SAFMR_1BR":3200,"SAFMR_2BR":3510,"SAFMR_3BR":4400,"SAFMR_4BR":4780}},{"attributes":{"ID":"10538","SAFMR_0BR":2850,"SAFMR_1BR":2990,"SAFMR_2BR":3280,"SAFMR_3BR":4110,"SAFMR_4BR":4460}},{"attributes":{"ID":"10540","SAFMR_0BR":3120,"SAFMR_1BR":3270,"SAFMR_2BR":3590,"SAFMR_3BR":4490,"SAFMR_4BR":4880}},{"attributes":{"ID":"10541","SAFMR_0BR":2550,"SAFMR_1BR":2680,"SAFMR_2BR":2940,"SAFMR_3BR":3680,"SAFMR_4BR":4000}},{"attributes":{"ID":"10542","SAFMR_0BR":2420,"SAFMR_1BR":2550,"SAFMR_2BR":2790,"SAFMR_3BR":3490,"SAFMR_4BR":3800}},{"attributes":{"ID":"10543","SAFMR_0BR":2790,"SAFMR_1BR":2930,"SAFMR_2BR":3210,"SAFMR_3BR":4020,"SAFMR_4BR":4370}},{"attributes":{"ID":"10545","SAFMR_0BR":2800,"SAFMR_1BR":2940,"SAFMR_2BR":3220,"SAFMR_3BR":4030,"SAFMR_4BR":4380}},{"attributes":{"ID":"10546","SAFMR_0BR":3140,"SAFMR_1BR":3290,"SAFMR_2BR":3610,"SAFMR_3BR":4520,"SAFMR_4BR":4910}},{"attributes":{"ID":"10547","SAFMR_0BR":2820,"SAFMR_1BR":2960,"SAFMR_2BR":3250,"SAFMR_3BR":4070,"SAFMR_4BR":4420}},{"attributes":{"ID":"10548","SAFMR_0BR":2400,"SAFMR_1BR":2520,"SAFMR_2BR":2760,"SAFMR_3BR":3460,"SAFMR_4BR":3760}},{"attributes":{"ID":"10549","SAFMR_0BR":2480,"SAFMR_1BR":2600,"SAFMR_2BR":2850,"SAFMR_3BR":3570,"SAFMR_4BR":3880}},{"attributes":{"ID":"10550","SAFMR_0BR":2370,"SAFMR_1BR":2490,"SAFMR_2BR":2730,"SAFMR_3BR":3420,"SAFMR_4BR":3710}},{"attributes":{"ID":"10551","SAFMR_0BR":2560,"SAFMR_1BR":2690,"SAFMR_2BR":2950,"SAFMR_3BR":3690,"SAFMR_4BR":4010}},{"attributes":{"ID":"10552","SAFMR_0BR":2370,"SAFMR_1BR":2490,"SAFMR_2BR":2730,"SAFMR_3BR":3420,"SAFMR_4BR":3710}},{"attributes":{"ID":"10553","SAFMR_0BR":2390,"SAFMR_1BR":2510,"SAFMR_2BR":2750,"SAFMR_3BR":3440,"SAFMR_4BR":3740}},{"attributes":{"ID":"10560","SAFMR_0BR":3060,"SAFMR_1BR":3210,"SAFMR_2BR":3520,"SAFMR_3BR":4410,"SAFMR_4BR":4790}},{"attributes":{"ID":"10562","SAFMR_0BR":2800,"SAFMR_1BR":2940,"SAFMR_2BR":3220,"SAFMR_3BR":4030,"SAFMR_4BR":4380}},{"attributes":{"ID":"10566","SAFMR_0BR":2570,"SAFMR_1BR":2700,"SAFMR_2BR":2960,"SAFMR_3BR":3710,"SAFMR_4BR":4030}},{"attributes":{"ID":"10567","SAFMR_0BR":2830,"SAFMR_1BR":2970,"SAFMR_2BR":3260,"SAFMR_3BR":4080,"SAFMR_4BR":4440}},{"attributes":{"ID":"10570","SAFMR_0BR":2580,"SAFMR_1BR":2710,"SAFMR_2BR":2970,"SAFMR_3BR":3720,"SAFMR_4BR":4040}},{"attributes":{"ID":"10573","SAFMR_0BR":2750,"SAFMR_1BR":2890,"SAFMR_2BR":3170,"SAFMR_3BR":3970,"SAFMR_4BR":4310}},{"attributes":{"ID":"10576","SAFMR_0BR":3400,"SAFMR_1BR":3620,"SAFMR_2BR":4000,"SAFMR_3BR":4990,"SAFMR_4BR":5470}},{"attributes":{"ID":"10577","SAFMR_0BR":2900,"SAFMR_1BR":3050,"SAFMR_2BR":3340,"SAFMR_3BR":4180,"SAFMR_4BR":4540}},{"attributes":{"ID":"10578","SAFMR_0BR":3430,"SAFMR_1BR":3600,"SAFMR_2BR":3950,"SAFMR_3BR":4940,"SAFMR_4BR":5370}},{"attributes":{"ID":"10579","SAFMR_0BR":3160,"SAFMR_1BR":3320,"SAFMR_2BR":3640,"SAFMR_3BR":4560,"SAFMR_4BR":4950}},{"attributes":{"ID":"10580","SAFMR_0BR":3800,"SAFMR_1BR":3990,"SAFMR_2BR":4370,"SAFMR_3BR":5470,"SAFMR_4BR":5950}},{"attributes":{"ID":"10583","SAFMR_0BR":3280,"SAFMR_1BR":3440,"SAFMR_2BR":3770,"SAFMR_3BR":4720,"SAFMR_4BR":5130}},{"attributes":{"ID":"10587","SAFMR_0BR":2560,"SAFMR_1BR":2690,"SAFMR_2BR":2950,"SAFMR_3BR":3690,"SAFMR_4BR":4010}},{"attributes":{"ID":"10588","SAFMR_0BR":2170,"SAFMR_1BR":2260,"SAFMR_2BR":2510,"SAFMR_3BR":3120,"SAFMR_4BR":3370}},{"attributes":{"ID":"10589","SAFMR_0BR":3800,"SAFMR_1BR":3990,"SAFMR_2BR":4370,"SAFMR_3BR":5470,"SAFMR_4BR":5950}},{"attributes":{"ID":"10590","SAFMR_0BR":3190,"SAFMR_1BR":3350,"SAFMR_2BR":3670,"SAFMR_3BR":4600,"SAFMR_4BR":4990}},{"attributes":{"ID":"10591","SAFMR_0BR":2590,"SAFMR_1BR":2720,"SAFMR_2BR":2980,"SAFMR_3BR":3730,"SAFMR_4BR":4050}},{"attributes":{"ID":"10594","SAFMR_0BR":2740,"SAFMR_1BR":2870,"SAFMR_2BR":3150,"SAFMR_3BR":3940,"SAFMR_4BR":4290}},{"attributes":{"ID":"10595","SAFMR_0BR":2210,"SAFMR_1BR":2320,"SAFMR_2BR":2540,"SAFMR_3BR":3180,"SAFMR_4BR":3460}},{"attributes":{"ID":"10596","SAFMR_0BR":2300,"SAFMR_1BR":2420,"SAFMR_2BR":2650,"SAFMR_3BR":3320,"SAFMR_4BR":3610}},{"attributes":{"ID":"10597","SAFMR_0BR":3170,"SAFMR_1BR":3330,"SAFMR_2BR":3650,"SAFMR_3BR":4570,"SAFMR_4BR":4970}},{"attributes":{"ID":"10598","SAFMR_0BR":3240,"SAFMR_1BR":3400,"SAFMR_2BR":3730,"SAFMR_3BR":4670,"SAFMR_4BR":5070}},{"attributes":{"ID":"10601","SAFMR_0BR":2920,"SAFMR_1BR":3070,"SAFMR_2BR":3360,"SAFMR_3BR":4210,"SAFMR_4BR":4570}},{"attributes":{"ID":"10602","SAFMR_0BR":2560,"SAFMR_1BR":2690,"SAFMR_2BR":2950,"SAFMR_3BR":3690,"SAFMR_4BR":4010}},{"attributes":{"ID":"10603","SAFMR_0BR":2660,"SAFMR_1BR":2790,"SAFMR_2BR":3060,"SAFMR_3BR":3830,"SAFMR_4BR":4160}},{"attributes":{"ID":"10604","SAFMR_0BR":2810,"SAFMR_1BR":2950,"SAFMR_2BR":3230,"SAFMR_3BR":4040,"SAFMR_4BR":4390}},{"attributes":{"ID":"10605","SAFMR_0BR":2950,"SAFMR_1BR":3100,"SAFMR_2BR":3400,"SAFMR_3BR":4260,"SAFMR_4BR":4630}},{"attributes":{"ID":"10606","SAFMR_0BR":3280,"SAFMR_1BR":3440,"SAFMR_2BR":3770,"SAFMR_3BR":4720,"SAFMR_4BR":5130}},{"attributes":{"ID":"10607","SAFMR_0BR":2720,"SAFMR_1BR":2860,"SAFMR_2BR":3130,"SAFMR_3BR":3920,"SAFMR_4BR":4260}},{"attributes":{"ID":"10701","SAFMR_0BR":2580,"SAFMR_1BR":2710,"SAFMR_2BR":2970,"SAFMR_3BR":3720,"SAFMR_4BR":4040}},{"attributes":{"ID":"10702","SAFMR_0BR":2560,"SAFMR_1BR":2690,"SAFMR_2BR":2950,"SAFMR_3BR":3690,"SAFMR_4BR":4010}},{"attributes":{"ID":"10703","SAFMR_0BR":2290,"SAFMR_1BR":2400,"SAFMR_2BR":2630,"SAFMR_3BR":3290,"SAFMR_4BR":3580}},{"attributes":{"ID":"10704","SAFMR_0BR":2510,"SAFMR_1BR":2640,"SAFMR_2BR":2890,"SAFMR_3BR":3620,"SAFMR_4BR":3930}},{"attributes":{"ID":"10705","SAFMR_0BR":2490,"SAFMR_1BR":2610,"SAFMR_2BR":2860,"SAFMR_3BR":3580,"SAFMR_4BR":3890}},{"attributes":{"ID":"10706","SAFMR_0BR":2740,"SAFMR_1BR":2870,"SAFMR_2BR":3150,"SAFMR_3BR":3940,"SAFMR_4BR":4290}},{"attributes":{"ID":"10707","SAFMR_0BR":3250,"SAFMR_1BR":3410,"SAFMR_2BR":3740,"SAFMR_3BR":4680,"SAFMR_4BR":5090}},{"attributes":{"ID":"10708","SAFMR_0BR":2790,"SAFMR_1BR":2930,"SAFMR_2BR":3210,"SAFMR_3BR":4020,"SAFMR_4BR":4370}},{"attributes":{"ID":"10709","SAFMR_0BR":2720,"SAFMR_1BR":2860,"SAFMR_2BR":3130,"SAFMR_3BR":3920,"SAFMR_4BR":4260}},{"attributes":{"ID":"10710","SAFMR_0BR":2420,"SAFMR_1BR":2550,"SAFMR_2BR":2790,"SAFMR_3BR":3490,"SAFMR_4BR":3800}},{"attributes":{"ID":"10801","SAFMR_0BR":2550,"SAFMR_1BR":2680,"SAFMR_2BR":2940,"SAFMR_3BR":3680,"SAFMR_4BR":4000}},{"attributes":{"ID":"10802","SAFMR_0BR":2560,"SAFMR_1BR":2690,"SAFMR_2BR":2950,"SAFMR_3BR":3690,"SAFMR_4BR":4010}},{"attributes":{"ID":"10803","SAFMR_0BR":2930,"SAFMR_1BR":3070,"SAFMR_2BR":3370,"SAFMR_3BR":4220,"SAFMR_4BR":4590}},{"attributes":{"ID":"10804","SAFMR_0BR":3020,"SAFMR_1BR":3170,"SAFMR_2BR":3470,"SAFMR_3BR":4350,"SAFMR_4BR":4720}},{"attributes":{"ID":"10805","SAFMR_0BR":2590,"SAFMR_1BR":2720,"SAFMR_2BR":2980,"SAFMR_3BR":3730,"SAFMR_4BR":4050}},{"attributes":{"ID":"10901","SAFMR_0BR":2540,"SAFMR_1BR":2660,"SAFMR_2BR":2920,"SAFMR_3BR":3660,"SAFMR_4BR":3970}},{"attributes":{"ID":"10910","SAFMR_0BR":1390,"SAFMR_1BR":1580,"SAFMR_2BR":2020,"SAFMR_3BR":2560,"SAFMR_4BR":2750}},{"attributes":{"ID":"10911","SAFMR_0BR":2620,"SAFMR_1BR":2700,"SAFMR_2BR":3030,"SAFMR_3BR":3780,"SAFMR_4BR":4060}},{"attributes":{"ID":"10912","SAFMR_0BR":1390,"SAFMR_1BR":1580,"SAFMR_2BR":2020,"SAFMR_3BR":2560,"SAFMR_4BR":2750}},{"attributes":{"ID":"10913","SAFMR_0BR":2970,"SAFMR_1BR":3120,"SAFMR_2BR":3420,"SAFMR_3BR":4280,"SAFMR_4BR":4650}},{"attributes":{"ID":"10914","SAFMR_0BR":1410,"SAFMR_1BR":1600,"SAFMR_2BR":2050,"SAFMR_3BR":2590,"SAFMR_4BR":2780}},{"attributes":{"ID":"10915","SAFMR_0BR":1390,"SAFMR_1BR":1580,"SAFMR_2BR":2020,"SAFMR_3BR":2560,"SAFMR_4BR":2750}},{"attributes":{"ID":"10916","SAFMR_0BR":1380,"SAFMR_1BR":1570,"SAFMR_2BR":2000,"SAFMR_3BR":2540,"SAFMR_4BR":2730}},{"attributes":{"ID":"10917","SAFMR_0BR":1680,"SAFMR_1BR":1910,"SAFMR_2BR":2430,"SAFMR_3BR":3090,"SAFMR_4BR":3310}},{"attributes":{"ID":"10918","SAFMR_0BR":1470,"SAFMR_1BR":1670,"SAFMR_2BR":2130,"SAFMR_3BR":2700,"SAFMR_4BR":2900}},{"attributes":{"ID":"10919","SAFMR_0BR":1410,"SAFMR_1BR":1590,"SAFMR_2BR":2020,"SAFMR_3BR":2590,"SAFMR_4BR":2770}},{"attributes":{"ID":"10920","SAFMR_0BR":2760,"SAFMR_1BR":2900,"SAFMR_2BR":3180,"SAFMR_3BR":3980,"SAFMR_4BR":4330}},{"attributes":{"ID":"10921","SAFMR_0BR":1630,"SAFMR_1BR":1860,"SAFMR_2BR":2370,"SAFMR_3BR":3010,"SAFMR_4BR":3230}},{"attributes":{"ID":"10922","SAFMR_0BR":1290,"SAFMR_1BR":1480,"SAFMR_2BR":1890,"SAFMR_3BR":2410,"SAFMR_4BR":2600}},{"attributes":{"ID":"10923","SAFMR_0BR":2450,"SAFMR_1BR":2570,"SAFMR_2BR":2820,"SAFMR_3BR":3530,"SAFMR_4BR":3840}},{"attributes":{"ID":"10924","SAFMR_0BR":1340,"SAFMR_1BR":1530,"SAFMR_2BR":1950,"SAFMR_3BR":2470,"SAFMR_4BR":2650}},{"attributes":{"ID":"10925","SAFMR_0BR":1300,"SAFMR_1BR":1470,"SAFMR_2BR":1880,"SAFMR_3BR":2390,"SAFMR_4BR":2560}},{"attributes":{"ID":"10926","SAFMR_0BR":1760,"SAFMR_1BR":2000,"SAFMR_2BR":2550,"SAFMR_3BR":3240,"SAFMR_4BR":3470}},{"attributes":{"ID":"10927","SAFMR_0BR":2450,"SAFMR_1BR":2570,"SAFMR_2BR":2820,"SAFMR_3BR":3530,"SAFMR_4BR":3840}},{"attributes":{"ID":"10928","SAFMR_0BR":1520,"SAFMR_1BR":1720,"SAFMR_2BR":2200,"SAFMR_3BR":2790,"SAFMR_4BR":3000}},{"attributes":{"ID":"10930","SAFMR_0BR":1680,"SAFMR_1BR":1910,"SAFMR_2BR":2440,"SAFMR_3BR":3100,"SAFMR_4BR":3320}},{"attributes":{"ID":"10931","SAFMR_0BR":2720,"SAFMR_1BR":2860,"SAFMR_2BR":3130,"SAFMR_3BR":3920,"SAFMR_4BR":4260}},{"attributes":{"ID":"10932","SAFMR_0BR":1410,"SAFMR_1BR":1600,"SAFMR_2BR":2050,"SAFMR_3BR":2600,"SAFMR_4BR":2790}},{"attributes":{"ID":"10933","SAFMR_0BR":1490,"SAFMR_1BR":1700,"SAFMR_2BR":2170,"SAFMR_3BR":2750,"SAFMR_4BR":2950}},{"attributes":{"ID":"10940","SAFMR_0BR":1410,"SAFMR_1BR":1600,"SAFMR_2BR":2050,"SAFMR_3BR":2600,"SAFMR_4BR":2790}},{"attributes":{"ID":"10940","SAFMR_0BR":1410,"SAFMR_1BR":1600,"SAFMR_2BR":2050,"SAFMR_3BR":2600,"SAFMR_4BR":2790}},{"attributes":{"ID":"10941","SAFMR_0BR":1430,"SAFMR_1BR":1620,"SAFMR_2BR":2070,"SAFMR_3BR":2630,"SAFMR_4BR":2820}},{"attributes":{"ID":"10949","SAFMR_0BR":1390,"SAFMR_1BR":1580,"SAFMR_2BR":2020,"SAFMR_3BR":2560,"SAFMR_4BR":2750}},{"attributes":{"ID":"10950","SAFMR_0BR":1480,"SAFMR_1BR":1680,"SAFMR_2BR":2140,"SAFMR_3BR":2720,"SAFMR_4BR":2910}},{"attributes":{"ID":"10952","SAFMR_0BR":2390,"SAFMR_1BR":2510,"SAFMR_2BR":2750,"SAFMR_3BR":3440,"SAFMR_4BR":3740}},{"attributes":{"ID":"10953","SAFMR_0BR":1480,"SAFMR_1BR":1680,"SAFMR_2BR":2150,"SAFMR_3BR":2730,"SAFMR_4BR":2930}},{"attributes":{"ID":"10954","SAFMR_0BR":3050,"SAFMR_1BR":3200,"SAFMR_2BR":3510,"SAFMR_3BR":4400,"SAFMR_4BR":4780}},{"attributes":{"ID":"10956","SAFMR_0BR":2750,"SAFMR_1BR":2880,"SAFMR_2BR":3160,"SAFMR_3BR":3960,"SAFMR_4BR":4300}},{"attributes":{"ID":"10958","SAFMR_0BR":1820,"SAFMR_1BR":2070,"SAFMR_2BR":2640,"SAFMR_3BR":3350,"SAFMR_4BR":3590}},{"attributes":{"ID":"10959","SAFMR_0BR":1390,"SAFMR_1BR":1580,"SAFMR_2BR":2020,"SAFMR_3BR":2560,"SAFMR_4BR":2750}},{"attributes":{"ID":"10960","SAFMR_0BR":2950,"SAFMR_1BR":3090,"SAFMR_2BR":3390,"SAFMR_3BR":4250,"SAFMR_4BR":4610}},{"attributes":{"ID":"10962","SAFMR_0BR":2170,"SAFMR_1BR":2260,"SAFMR_2BR":2510,"SAFMR_3BR":3120,"SAFMR_4BR":3370}},{"attributes":{"ID":"10963","SAFMR_0BR":1180,"SAFMR_1BR":1350,"SAFMR_2BR":1720,"SAFMR_3BR":2190,"SAFMR_4BR":2370}},{"attributes":{"ID":"10963","SAFMR_0BR":1180,"SAFMR_1BR":1350,"SAFMR_2BR":1720,"SAFMR_3BR":2190,"SAFMR_4BR":2370}},{"attributes":{"ID":"10964","SAFMR_0BR":2350,"SAFMR_1BR":2560,"SAFMR_2BR":2870,"SAFMR_3BR":3550,"SAFMR_4BR":4180}},{"attributes":{"ID":"10965","SAFMR_0BR":2570,"SAFMR_1BR":2700,"SAFMR_2BR":2960,"SAFMR_3BR":3710,"SAFMR_4BR":4030}},{"attributes":{"ID":"10968","SAFMR_0BR":2820,"SAFMR_1BR":2960,"SAFMR_2BR":3240,"SAFMR_3BR":4060,"SAFMR_4BR":4410}},{"attributes":{"ID":"10969","SAFMR_0BR":1360,"SAFMR_1BR":1550,"SAFMR_2BR":1960,"SAFMR_3BR":2480,"SAFMR_4BR":2680}},{"attributes":{"ID":"10970","SAFMR_0BR":2360,"SAFMR_1BR":2480,"SAFMR_2BR":2720,"SAFMR_3BR":3410,"SAFMR_4BR":3700}},{"attributes":{"ID":"10973","SAFMR_0BR":1650,"SAFMR_1BR":1870,"SAFMR_2BR":2390,"SAFMR_3BR":3030,"SAFMR_4BR":3250}},{"attributes":{"ID":"10974","SAFMR_0BR":3070,"SAFMR_1BR":3220,"SAFMR_2BR":3530,"SAFMR_3BR":4420,"SAFMR_4BR":4800}},{"attributes":{"ID":"10974","SAFMR_0BR":3070,"SAFMR_1BR":3220,"SAFMR_2BR":3530,"SAFMR_3BR":4420,"SAFMR_4BR":4800}},{"attributes":{"ID":"10975","SAFMR_0BR":1880,"SAFMR_1BR":2140,"SAFMR_2BR":2730,"SAFMR_3BR":3460,"SAFMR_4BR":3720}},{"attributes":{"ID":"10976","SAFMR_0BR":2550,"SAFMR_1BR":2670,"SAFMR_2BR":2930,"SAFMR_3BR":3670,"SAFMR_4BR":3990}},{"attributes":{"ID":"10977","SAFMR_0BR":2210,"SAFMR_1BR":2320,"SAFMR_2BR":2540,"SAFMR_3BR":3180,"SAFMR_4BR":3460}},{"attributes":{"ID":"10979","SAFMR_0BR":1440,"SAFMR_1BR":1630,"SAFMR_2BR":2040,"SAFMR_3BR":2570,"SAFMR_4BR":2860}},{"attributes":{"ID":"10980","SAFMR_0BR":2360,"SAFMR_1BR":2480,"SAFMR_2BR":2720,"SAFMR_3BR":3410,"SAFMR_4BR":3700}},{"attributes":{"ID":"10981","SAFMR_0BR":1390,"SAFMR_1BR":1580,"SAFMR_2BR":2020,"SAFMR_3BR":2560,"SAFMR_4BR":2750}},{"attributes":{"ID":"10982","SAFMR_0BR":2530,"SAFMR_1BR":2650,"SAFMR_2BR":2910,"SAFMR_3BR":3640,"SAFMR_4BR":3960}},{"attributes":{"ID":"10983","SAFMR_0BR":2940,"SAFMR_1BR":3080,"SAFMR_2BR":3380,"SAFMR_3BR":4230,"SAFMR_4BR":4600}},{"attributes":{"ID":"10984","SAFMR_0BR":2400,"SAFMR_1BR":2520,"SAFMR_2BR":2770,"SAFMR_3BR":3470,"SAFMR_4BR":3770}},{"attributes":{"ID":"10985","SAFMR_0BR":1400,"SAFMR_1BR":1530,"SAFMR_2BR":1960,"SAFMR_3BR":2490,"SAFMR_4BR":2660}},{"attributes":{"ID":"10986","SAFMR_0BR":2620,"SAFMR_1BR":2700,"SAFMR_2BR":3030,"SAFMR_3BR":3780,"SAFMR_4BR":4060}},{"attributes":{"ID":"10987","SAFMR_0BR":2170,"SAFMR_1BR":2260,"SAFMR_2BR":2510,"SAFMR_3BR":3120,"SAFMR_4BR":3370}},{"attributes":{"ID":"10987","SAFMR_0BR":2170,"SAFMR_1BR":2260,"SAFMR_2BR":2510,"SAFMR_3BR":3120,"SAFMR_4BR":3370}},{"attributes":{"ID":"10988","SAFMR_0BR":1280,"SAFMR_1BR":1460,"SAFMR_2BR":1860,"SAFMR_3BR":2360,"SAFMR_4BR":2530}},{"attributes":{"ID":"10989","SAFMR_0BR":3010,"SAFMR_1BR":3160,"SAFMR_2BR":3460,"SAFMR_3BR":4330,"SAFMR_4BR":4710}},{"attributes":{"ID":"10990","SAFMR_0BR":1200,"SAFMR_1BR":1360,"SAFMR_2BR":1740,"SAFMR_3BR":2210,"SAFMR_4BR":2370}},{"attributes":{"ID":"10992","SAFMR_0BR":1340,"SAFMR_1BR":1520,"SAFMR_2BR":1940,"SAFMR_3BR":2460,"SAFMR_4BR":2640}},{"attributes":{"ID":"10993","SAFMR_0BR":2240,"SAFMR_1BR":2350,"SAFMR_2BR":2580,"SAFMR_3BR":3230,"SAFMR_4BR":3510}},{"attributes":{"ID":"10994","SAFMR_0BR":2470,"SAFMR_1BR":2580,"SAFMR_2BR":2850,"SAFMR_3BR":3550,"SAFMR_4BR":3830}},{"attributes":{"ID":"10996","SAFMR_0BR":2050,"SAFMR_1BR":2320,"SAFMR_2BR":2970,"SAFMR_3BR":3770,"SAFMR_4BR":4040}},{"attributes":{"ID":"10998","SAFMR_0BR":1430,"SAFMR_1BR":1630,"SAFMR_2BR":2080,"SAFMR_3BR":2640,"SAFMR_4BR":2830}},{"attributes":{"ID":"11001","SAFMR_0BR":2170,"SAFMR_1BR":2410,"SAFMR_2BR":2750,"SAFMR_3BR":3550,"SAFMR_4BR":3770}},{"attributes":{"ID":"11001","SAFMR_0BR":2170,"SAFMR_1BR":2410,"SAFMR_2BR":2750,"SAFMR_3BR":3550,"SAFMR_4BR":3770}},{"attributes":{"ID":"11002","SAFMR_0BR":2020,"SAFMR_1BR":2410,"SAFMR_2BR":2780,"SAFMR_3BR":3610,"SAFMR_4BR":3810}},{"attributes":{"ID":"11003","SAFMR_0BR":2100,"SAFMR_1BR":2500,"SAFMR_2BR":2890,"SAFMR_3BR":3750,"SAFMR_4BR":3960}},{"attributes":{"ID":"11004","SAFMR_0BR":2660,"SAFMR_1BR":2790,"SAFMR_2BR":3060,"SAFMR_3BR":3830,"SAFMR_4BR":4160}},{"attributes":{"ID":"11004","SAFMR_0BR":2660,"SAFMR_1BR":2790,"SAFMR_2BR":3060,"SAFMR_3BR":3830,"SAFMR_4BR":4160}},{"attributes":{"ID":"11005","SAFMR_0BR":3020,"SAFMR_1BR":3170,"SAFMR_2BR":3480,"SAFMR_3BR":4360,"SAFMR_4BR":4730}},{"attributes":{"ID":"11005","SAFMR_0BR":3020,"SAFMR_1BR":3170,"SAFMR_2BR":3480,"SAFMR_3BR":4360,"SAFMR_4BR":4730}},{"attributes":{"ID":"11010","SAFMR_0BR":1870,"SAFMR_1BR":2230,"SAFMR_2BR":2580,"SAFMR_3BR":3350,"SAFMR_4BR":3540}},{"attributes":{"ID":"11020","SAFMR_0BR":2400,"SAFMR_1BR":2870,"SAFMR_2BR":3310,"SAFMR_3BR":4290,"SAFMR_4BR":4540}},{"attributes":{"ID":"11020","SAFMR_0BR":2400,"SAFMR_1BR":2870,"SAFMR_2BR":3310,"SAFMR_3BR":4290,"SAFMR_4BR":4540}},{"attributes":{"ID":"11021","SAFMR_0BR":1940,"SAFMR_1BR":2320,"SAFMR_2BR":2680,"SAFMR_3BR":3480,"SAFMR_4BR":3680}},{"attributes":{"ID":"11022","SAFMR_0BR":2020,"SAFMR_1BR":2410,"SAFMR_2BR":2780,"SAFMR_3BR":3610,"SAFMR_4BR":3810}},{"attributes":{"ID":"11023","SAFMR_0BR":2090,"SAFMR_1BR":2500,"SAFMR_2BR":2890,"SAFMR_3BR":3750,"SAFMR_4BR":3970}},{"attributes":{"ID":"11024","SAFMR_0BR":2340,"SAFMR_1BR":2800,"SAFMR_2BR":3230,"SAFMR_3BR":4190,"SAFMR_4BR":4430}},{"attributes":{"ID":"11030","SAFMR_0BR":2180,"SAFMR_1BR":2610,"SAFMR_2BR":3010,"SAFMR_3BR":3900,"SAFMR_4BR":4130}},{"attributes":{"ID":"11040","SAFMR_0BR":2250,"SAFMR_1BR":2660,"SAFMR_2BR":3060,"SAFMR_3BR":3960,"SAFMR_4BR":4190}},{"attributes":{"ID":"11040","SAFMR_0BR":2250,"SAFMR_1BR":2660,"SAFMR_2BR":3060,"SAFMR_3BR":3960,"SAFMR_4BR":4190}},{"attributes":{"ID":"11042","SAFMR_0BR":2390,"SAFMR_1BR":2790,"SAFMR_2BR":3190,"SAFMR_3BR":4110,"SAFMR_4BR":4370}},{"attributes":{"ID":"11050","SAFMR_0BR":2260,"SAFMR_1BR":2700,"SAFMR_2BR":3120,"SAFMR_3BR":4050,"SAFMR_4BR":4280}},{"attributes":{"ID":"11096","SAFMR_0BR":1750,"SAFMR_1BR":2090,"SAFMR_2BR":2410,"SAFMR_3BR":3130,"SAFMR_4BR":3310}},{"attributes":{"ID":"11101","SAFMR_0BR":3350,"SAFMR_1BR":3510,"SAFMR_2BR":3850,"SAFMR_3BR":4820,"SAFMR_4BR":5240}},{"attributes":{"ID":"11102","SAFMR_0BR":3360,"SAFMR_1BR":3530,"SAFMR_2BR":3870,"SAFMR_3BR":4850,"SAFMR_4BR":5270}},{"attributes":{"ID":"11103","SAFMR_0BR":3010,"SAFMR_1BR":3160,"SAFMR_2BR":3460,"SAFMR_3BR":4330,"SAFMR_4BR":4710}},{"attributes":{"ID":"11104","SAFMR_0BR":2800,"SAFMR_1BR":2940,"SAFMR_2BR":3220,"SAFMR_3BR":4030,"SAFMR_4BR":4380}},{"attributes":{"ID":"11105","SAFMR_0BR":3190,"SAFMR_1BR":3350,"SAFMR_2BR":3670,"SAFMR_3BR":4600,"SAFMR_4BR":4990}},{"attributes":{"ID":"11106","SAFMR_0BR":2890,"SAFMR_1BR":3030,"SAFMR_2BR":3320,"SAFMR_3BR":4160,"SAFMR_4BR":4520}},{"attributes":{"ID":"11109","SAFMR_0BR":3350,"SAFMR_1BR":3510,"SAFMR_2BR":3850,"SAFMR_3BR":4820,"SAFMR_4BR":5240}},{"attributes":{"ID":"11201","SAFMR_0BR":3800,"SAFMR_1BR":3990,"SAFMR_2BR":4370,"SAFMR_3BR":5470,"SAFMR_4BR":5950}},{"attributes":{"ID":"11202","SAFMR_0BR":2530,"SAFMR_1BR":2650,"SAFMR_2BR":2910,"SAFMR_3BR":3640,"SAFMR_4BR":3960}},{"attributes":{"ID":"11203","SAFMR_0BR":2350,"SAFMR_1BR":2460,"SAFMR_2BR":2700,"SAFMR_3BR":3380,"SAFMR_4BR":3670}},{"attributes":{"ID":"11204","SAFMR_0BR":2430,"SAFMR_1BR":2550,"SAFMR_2BR":2800,"SAFMR_3BR":3510,"SAFMR_4BR":3810}},{"attributes":{"ID":"11205","SAFMR_0BR":3020,"SAFMR_1BR":3170,"SAFMR_2BR":3470,"SAFMR_3BR":4350,"SAFMR_4BR":4720}},{"attributes":{"ID":"11206","SAFMR_0BR":2300,"SAFMR_1BR":2420,"SAFMR_2BR":2650,"SAFMR_3BR":3320,"SAFMR_4BR":3610}},{"attributes":{"ID":"11207","SAFMR_0BR":2230,"SAFMR_1BR":2340,"SAFMR_2BR":2570,"SAFMR_3BR":3220,"SAFMR_4BR":3500}},{"attributes":{"ID":"11208","SAFMR_0BR":2330,"SAFMR_1BR":2440,"SAFMR_2BR":2680,"SAFMR_3BR":3360,"SAFMR_4BR":3650}},{"attributes":{"ID":"11209","SAFMR_0BR":2820,"SAFMR_1BR":2960,"SAFMR_2BR":3240,"SAFMR_3BR":4060,"SAFMR_4BR":4410}},{"attributes":{"ID":"11210","SAFMR_0BR":2430,"SAFMR_1BR":2550,"SAFMR_2BR":2800,"SAFMR_3BR":3510,"SAFMR_4BR":3810}},{"attributes":{"ID":"11211","SAFMR_0BR":3140,"SAFMR_1BR":3290,"SAFMR_2BR":3610,"SAFMR_3BR":4520,"SAFMR_4BR":4910}},{"attributes":{"ID":"11212","SAFMR_0BR":2170,"SAFMR_1BR":2260,"SAFMR_2BR":2510,"SAFMR_3BR":3120,"SAFMR_4BR":3370}},{"attributes":{"ID":"11213","SAFMR_0BR":2440,"SAFMR_1BR":2560,"SAFMR_2BR":2810,"SAFMR_3BR":3520,"SAFMR_4BR":3820}},{"attributes":{"ID":"11214","SAFMR_0BR":2440,"SAFMR_1BR":2560,"SAFMR_2BR":2810,"SAFMR_3BR":3520,"SAFMR_4BR":3820}},{"attributes":{"ID":"11215","SAFMR_0BR":3800,"SAFMR_1BR":3990,"SAFMR_2BR":4370,"SAFMR_3BR":5470,"SAFMR_4BR":5950}},{"attributes":{"ID":"11216","SAFMR_0BR":3190,"SAFMR_1BR":3350,"SAFMR_2BR":3670,"SAFMR_3BR":4600,"SAFMR_4BR":4990}},{"attributes":{"ID":"11217","SAFMR_0BR":3800,"SAFMR_1BR":3990,"SAFMR_2BR":4370,"SAFMR_3BR":5470,"SAFMR_4BR":5950}},{"attributes":{"ID":"11218","SAFMR_0BR":2770,"SAFMR_1BR":2910,"SAFMR_2BR":3190,"SAFMR_3BR":3990,"SAFMR_4BR":4340}},{"attributes":{"ID":"11219","SAFMR_0BR":2330,"SAFMR_1BR":2440,"SAFMR_2BR":2680,"SAFMR_3BR":3360,"SAFMR_4BR":3650}},{"attributes":{"ID":"11220","SAFMR_0BR":2250,"SAFMR_1BR":2360,"SAFMR_2BR":2590,"SAFMR_3BR":3240,"SAFMR_4BR":3520}},{"attributes":{"ID":"11221","SAFMR_0BR":2750,"SAFMR_1BR":2880,"SAFMR_2BR":3160,"SAFMR_3BR":3960,"SAFMR_4BR":4300}},{"attributes":{"ID":"11222","SAFMR_0BR":3460,"SAFMR_1BR":3630,"SAFMR_2BR":3980,"SAFMR_3BR":4980,"SAFMR_4BR":5420}},{"attributes":{"ID":"11223","SAFMR_0BR":2500,"SAFMR_1BR":2630,"SAFMR_2BR":2880,"SAFMR_3BR":3610,"SAFMR_4BR":3920}},{"attributes":{"ID":"11224","SAFMR_0BR":2170,"SAFMR_1BR":2260,"SAFMR_2BR":2510,"SAFMR_3BR":3120,"SAFMR_4BR":3370}},{"attributes":{"ID":"11225","SAFMR_0BR":2520,"SAFMR_1BR":2650,"SAFMR_2BR":2900,"SAFMR_3BR":3630,"SAFMR_4BR":3950}},{"attributes":{"ID":"11226","SAFMR_0BR":2430,"SAFMR_1BR":2550,"SAFMR_2BR":2800,"SAFMR_3BR":3510,"SAFMR_4BR":3810}},{"attributes":{"ID":"11228","SAFMR_0BR":2430,"SAFMR_1BR":2550,"SAFMR_2BR":2800,"SAFMR_3BR":3510,"SAFMR_4BR":3810}},{"attributes":{"ID":"11229","SAFMR_0BR":2490,"SAFMR_1BR":2610,"SAFMR_2BR":2860,"SAFMR_3BR":3580,"SAFMR_4BR":3890}},{"attributes":{"ID":"11230","SAFMR_0BR":2650,"SAFMR_1BR":2780,"SAFMR_2BR":3050,"SAFMR_3BR":3820,"SAFMR_4BR":4150}},{"attributes":{"ID":"11231","SAFMR_0BR":3800,"SAFMR_1BR":3990,"SAFMR_2BR":4370,"SAFMR_3BR":5470,"SAFMR_4BR":5950}},{"attributes":{"ID":"11232","SAFMR_0BR":2490,"SAFMR_1BR":2610,"SAFMR_2BR":2860,"SAFMR_3BR":3580,"SAFMR_4BR":3890}},{"attributes":{"ID":"11233","SAFMR_0BR":2370,"SAFMR_1BR":2490,"SAFMR_2BR":2730,"SAFMR_3BR":3420,"SAFMR_4BR":3710}},{"attributes":{"ID":"11234","SAFMR_0BR":2520,"SAFMR_1BR":2650,"SAFMR_2BR":2900,"SAFMR_3BR":3630,"SAFMR_4BR":3950}},{"attributes":{"ID":"11235","SAFMR_0BR":2480,"SAFMR_1BR":2600,"SAFMR_2BR":2850,"SAFMR_3BR":3570,"SAFMR_4BR":3880}},{"attributes":{"ID":"11236","SAFMR_0BR":2440,"SAFMR_1BR":2560,"SAFMR_2BR":2810,"SAFMR_3BR":3520,"SAFMR_4BR":3820}},{"attributes":{"ID":"11237","SAFMR_0BR":2620,"SAFMR_1BR":2750,"SAFMR_2BR":3020,"SAFMR_3BR":3780,"SAFMR_4BR":4110}},{"attributes":{"ID":"11238","SAFMR_0BR":3610,"SAFMR_1BR":3790,"SAFMR_2BR":4160,"SAFMR_3BR":5210,"SAFMR_4BR":5660}},{"attributes":{"ID":"11239","SAFMR_0BR":2170,"SAFMR_1BR":2260,"SAFMR_2BR":2510,"SAFMR_3BR":3120,"SAFMR_4BR":3370}},{"attributes":{"ID":"11241","SAFMR_0BR":2530,"SAFMR_1BR":2650,"SAFMR_2BR":2910,"SAFMR_3BR":3640,"SAFMR_4BR":3960}},{"attributes":{"ID":"11242","SAFMR_0BR":2530,"SAFMR_1BR":2650,"SAFMR_2BR":2910,"SAFMR_3BR":3640,"SAFMR_4BR":3960}},{"attributes":{"ID":"11243","SAFMR_0BR":2530,"SAFMR_1BR":2650,"SAFMR_2BR":2910,"SAFMR_3BR":3640,"SAFMR_4BR":3960}},{"attributes":{"ID":"11247","SAFMR_0BR":2530,"SAFMR_1BR":2650,"SAFMR_2BR":2910,"SAFMR_3BR":3640,"SAFMR_4BR":3960}},{"attributes":{"ID":"11249","SAFMR_0BR":2990,"SAFMR_1BR":3140,"SAFMR_2BR":3440,"SAFMR_3BR":4310,"SAFMR_4BR":4680}},{"attributes":{"ID":"11252","SAFMR_0BR":2530,"SAFMR_1BR":2650,"SAFMR_2BR":2910,"SAFMR_3BR":3640,"SAFMR_4BR":3960}},{"attributes":{"ID":"11256","SAFMR_0BR":2530,"SAFMR_1BR":2650,"SAFMR_2BR":2910,"SAFMR_3BR":3640,"SAFMR_4BR":3960}},{"attributes":{"ID":"11351","SAFMR_0BR":2600,"SAFMR_1BR":2730,"SAFMR_2BR":2990,"SAFMR_3BR":3740,"SAFMR_4BR":4070}},{"attributes":{"ID":"11352","SAFMR_0BR":2600,"SAFMR_1BR":2730,"SAFMR_2BR":2990,"SAFMR_3BR":3740,"SAFMR_4BR":4070}},{"attributes":{"ID":"11354","SAFMR_0BR":2620,"SAFMR_1BR":2750,"SAFMR_2BR":3020,"SAFMR_3BR":3780,"SAFMR_4BR":4110}},{"attributes":{"ID":"11355","SAFMR_0BR":2620,"SAFMR_1BR":2750,"SAFMR_2BR":3010,"SAFMR_3BR":3770,"SAFMR_4BR":4100}},{"attributes":{"ID":"11356","SAFMR_0BR":2820,"SAFMR_1BR":2960,"SAFMR_2BR":3250,"SAFMR_3BR":4070,"SAFMR_4BR":4420}},{"attributes":{"ID":"11357","SAFMR_0BR":2950,"SAFMR_1BR":3090,"SAFMR_2BR":3390,"SAFMR_3BR":4250,"SAFMR_4BR":4610}},{"attributes":{"ID":"11358","SAFMR_0BR":2810,"SAFMR_1BR":2950,"SAFMR_2BR":3230,"SAFMR_3BR":4040,"SAFMR_4BR":4390}},{"attributes":{"ID":"11359","SAFMR_0BR":2600,"SAFMR_1BR":2730,"SAFMR_2BR":2990,"SAFMR_3BR":3740,"SAFMR_4BR":4070}},{"attributes":{"ID":"11360","SAFMR_0BR":3190,"SAFMR_1BR":3350,"SAFMR_2BR":3670,"SAFMR_3BR":4600,"SAFMR_4BR":4990}},{"attributes":{"ID":"11361","SAFMR_0BR":3130,"SAFMR_1BR":3280,"SAFMR_2BR":3600,"SAFMR_3BR":4510,"SAFMR_4BR":4900}},{"attributes":{"ID":"11362","SAFMR_0BR":3400,"SAFMR_1BR":3570,"SAFMR_2BR":3910,"SAFMR_3BR":4900,"SAFMR_4BR":5320}},{"attributes":{"ID":"11363","SAFMR_0BR":3110,"SAFMR_1BR":3270,"SAFMR_2BR":3580,"SAFMR_3BR":4480,"SAFMR_4BR":4870}},{"attributes":{"ID":"11363","SAFMR_0BR":3110,"SAFMR_1BR":3270,"SAFMR_2BR":3580,"SAFMR_3BR":4480,"SAFMR_4BR":4870}},{"attributes":{"ID":"11364","SAFMR_0BR":3070,"SAFMR_1BR":3220,"SAFMR_2BR":3530,"SAFMR_3BR":4420,"SAFMR_4BR":4800}},{"attributes":{"ID":"11365","SAFMR_0BR":2360,"SAFMR_1BR":2480,"SAFMR_2BR":2720,"SAFMR_3BR":3410,"SAFMR_4BR":3700}},{"attributes":{"ID":"11366","SAFMR_0BR":2710,"SAFMR_1BR":2850,"SAFMR_2BR":3120,"SAFMR_3BR":3910,"SAFMR_4BR":4240}},{"attributes":{"ID":"11367","SAFMR_0BR":2370,"SAFMR_1BR":2490,"SAFMR_2BR":2730,"SAFMR_3BR":3420,"SAFMR_4BR":3710}},{"attributes":{"ID":"11368","SAFMR_0BR":2690,"SAFMR_1BR":2830,"SAFMR_2BR":3100,"SAFMR_3BR":3880,"SAFMR_4BR":4220}},{"attributes":{"ID":"11369","SAFMR_0BR":2660,"SAFMR_1BR":2790,"SAFMR_2BR":3060,"SAFMR_3BR":3830,"SAFMR_4BR":4160}},{"attributes":{"ID":"11370","SAFMR_0BR":2770,"SAFMR_1BR":2910,"SAFMR_2BR":3190,"SAFMR_3BR":3990,"SAFMR_4BR":4340}},{"attributes":{"ID":"11371","SAFMR_0BR":2600,"SAFMR_1BR":2730,"SAFMR_2BR":2990,"SAFMR_3BR":3740,"SAFMR_4BR":4070}},{"attributes":{"ID":"11372","SAFMR_0BR":2690,"SAFMR_1BR":2830,"SAFMR_2BR":3100,"SAFMR_3BR":3880,"SAFMR_4BR":4220}},{"attributes":{"ID":"11373","SAFMR_0BR":2750,"SAFMR_1BR":2890,"SAFMR_2BR":3170,"SAFMR_3BR":3970,"SAFMR_4BR":4310}},{"attributes":{"ID":"11374","SAFMR_0BR":3130,"SAFMR_1BR":3280,"SAFMR_2BR":3600,"SAFMR_3BR":4510,"SAFMR_4BR":4900}},{"attributes":{"ID":"11375","SAFMR_0BR":3170,"SAFMR_1BR":3330,"SAFMR_2BR":3650,"SAFMR_3BR":4570,"SAFMR_4BR":4970}},{"attributes":{"ID":"11377","SAFMR_0BR":2620,"SAFMR_1BR":2750,"SAFMR_2BR":3020,"SAFMR_3BR":3780,"SAFMR_4BR":4110}},{"attributes":{"ID":"11378","SAFMR_0BR":2690,"SAFMR_1BR":2820,"SAFMR_2BR":3090,"SAFMR_3BR":3870,"SAFMR_4BR":4200}},{"attributes":{"ID":"11379","SAFMR_0BR":2820,"SAFMR_1BR":2960,"SAFMR_2BR":3240,"SAFMR_3BR":4060,"SAFMR_4BR":4410}},{"attributes":{"ID":"11380","SAFMR_0BR":2600,"SAFMR_1BR":2730,"SAFMR_2BR":2990,"SAFMR_3BR":3740,"SAFMR_4BR":4070}},{"attributes":{"ID":"11385","SAFMR_0BR":2570,"SAFMR_1BR":2700,"SAFMR_2BR":2960,"SAFMR_3BR":3710,"SAFMR_4BR":4030}},{"attributes":{"ID":"11386","SAFMR_0BR":2600,"SAFMR_1BR":2730,"SAFMR_2BR":2990,"SAFMR_3BR":3740,"SAFMR_4BR":4070}},{"attributes":{"ID":"11411","SAFMR_0BR":2250,"SAFMR_1BR":2360,"SAFMR_2BR":2590,"SAFMR_3BR":3240,"SAFMR_4BR":3520}},{"attributes":{"ID":"11412","SAFMR_0BR":2240,"SAFMR_1BR":2350,"SAFMR_2BR":2580,"SAFMR_3BR":3230,"SAFMR_4BR":3510}},{"attributes":{"ID":"11413","SAFMR_0BR":2710,"SAFMR_1BR":2850,"SAFMR_2BR":3120,"SAFMR_3BR":3910,"SAFMR_4BR":4240}},{"attributes":{"ID":"11414","SAFMR_0BR":2690,"SAFMR_1BR":2820,"SAFMR_2BR":3090,"SAFMR_3BR":3870,"SAFMR_4BR":4200}},{"attributes":{"ID":"11415","SAFMR_0BR":2790,"SAFMR_1BR":2930,"SAFMR_2BR":3210,"SAFMR_3BR":4020,"SAFMR_4BR":4370}},{"attributes":{"ID":"11416","SAFMR_0BR":2550,"SAFMR_1BR":2670,"SAFMR_2BR":2930,"SAFMR_3BR":3670,"SAFMR_4BR":3990}},{"attributes":{"ID":"11417","SAFMR_0BR":2550,"SAFMR_1BR":2670,"SAFMR_2BR":2930,"SAFMR_3BR":3670,"SAFMR_4BR":3990}},{"attributes":{"ID":"11418","SAFMR_0BR":2620,"SAFMR_1BR":2750,"SAFMR_2BR":3010,"SAFMR_3BR":3770,"SAFMR_4BR":4100}},{"attributes":{"ID":"11419","SAFMR_0BR":2700,"SAFMR_1BR":2840,"SAFMR_2BR":3110,"SAFMR_3BR":3890,"SAFMR_4BR":4230}},{"attributes":{"ID":"11420","SAFMR_0BR":2740,"SAFMR_1BR":2870,"SAFMR_2BR":3150,"SAFMR_3BR":3940,"SAFMR_4BR":4290}},{"attributes":{"ID":"11421","SAFMR_0BR":2680,"SAFMR_1BR":2810,"SAFMR_2BR":3080,"SAFMR_3BR":3860,"SAFMR_4BR":4190}},{"attributes":{"ID":"11422","SAFMR_0BR":3010,"SAFMR_1BR":3160,"SAFMR_2BR":3460,"SAFMR_3BR":4330,"SAFMR_4BR":4710}},{"attributes":{"ID":"11423","SAFMR_0BR":2260,"SAFMR_1BR":2370,"SAFMR_2BR":2600,"SAFMR_3BR":3260,"SAFMR_4BR":3540}},{"attributes":{"ID":"11424","SAFMR_0BR":2600,"SAFMR_1BR":2730,"SAFMR_2BR":2990,"SAFMR_3BR":3740,"SAFMR_4BR":4070}},{"attributes":{"ID":"11426","SAFMR_0BR":2890,"SAFMR_1BR":3040,"SAFMR_2BR":3330,"SAFMR_3BR":4170,"SAFMR_4BR":4530}},{"attributes":{"ID":"11427","SAFMR_0BR":2300,"SAFMR_1BR":2420,"SAFMR_2BR":2650,"SAFMR_3BR":3320,"SAFMR_4BR":3610}},{"attributes":{"ID":"11428","SAFMR_0BR":2420,"SAFMR_1BR":2540,"SAFMR_2BR":2780,"SAFMR_3BR":3480,"SAFMR_4BR":3780}},{"attributes":{"ID":"11429","SAFMR_0BR":2260,"SAFMR_1BR":2370,"SAFMR_2BR":2600,"SAFMR_3BR":3260,"SAFMR_4BR":3540}},{"attributes":{"ID":"11430","SAFMR_0BR":2390,"SAFMR_1BR":2550,"SAFMR_2BR":2810,"SAFMR_3BR":3540,"SAFMR_4BR":3830}},{"attributes":{"ID":"11431","SAFMR_0BR":2600,"SAFMR_1BR":2730,"SAFMR_2BR":2990,"SAFMR_3BR":3740,"SAFMR_4BR":4070}},{"attributes":{"ID":"11432","SAFMR_0BR":2750,"SAFMR_1BR":2890,"SAFMR_2BR":3170,"SAFMR_3BR":3970,"SAFMR_4BR":4310}},{"attributes":{"ID":"11433","SAFMR_0BR":2270,"SAFMR_1BR":2380,"SAFMR_2BR":2610,"SAFMR_3BR":3270,"SAFMR_4BR":3550}},{"attributes":{"ID":"11434","SAFMR_0BR":2170,"SAFMR_1BR":2260,"SAFMR_2BR":2510,"SAFMR_3BR":3120,"SAFMR_4BR":3370}},{"attributes":{"ID":"11435","SAFMR_0BR":2550,"SAFMR_1BR":2680,"SAFMR_2BR":2940,"SAFMR_3BR":3680,"SAFMR_4BR":4000}},{"attributes":{"ID":"11436","SAFMR_0BR":2780,"SAFMR_1BR":2920,"SAFMR_2BR":3200,"SAFMR_3BR":4010,"SAFMR_4BR":4350}},{"attributes":{"ID":"11437","SAFMR_0BR":2600,"SAFMR_1BR":2730,"SAFMR_2BR":2990,"SAFMR_3BR":3740,"SAFMR_4BR":4070}},{"attributes":{"ID":"11439","SAFMR_0BR":2740,"SAFMR_1BR":2880,"SAFMR_2BR":3160,"SAFMR_3BR":3960,"SAFMR_4BR":4290}},{"attributes":{"ID":"11451","SAFMR_0BR":2600,"SAFMR_1BR":2730,"SAFMR_2BR":2990,"SAFMR_3BR":3740,"SAFMR_4BR":4070}},{"attributes":{"ID":"11501","SAFMR_0BR":2000,"SAFMR_1BR":2390,"SAFMR_2BR":2760,"SAFMR_3BR":3580,"SAFMR_4BR":3790}},{"attributes":{"ID":"11507","SAFMR_0BR":2440,"SA